{
    "markers": [
        {
            "id": 238,
            "corners": [
                {
                    "x": 5.3750036621093750e+02,
                    "y": 2.0391941833496094e+02
                },
                {
                    "x": 5.8106127929687500e+02,
                    "y": 2.5659851074218750e+02
                },
                {
                    "x": 5.2530426025390625e+02,
                    "y": 2.8924249267578125e+02
                },
                {
                    "x": 4.8235903930664062e+02,
                    "y": 2.3334799194335938e+02
                }
            ]
        },
        {
            "id": 239,
            "corners": [
                {
                    "x": 2.3346765136718750e+02,
                    "y": 2.9786581420898438e+02
                },
                {
                    "x": 1.4061744689941406e+02,
                    "y": 2.7963208007812500e+02
                },
                {
                    "x": 1.7323255920410156e+02,
                    "y": 2.0939347839355469e+02
                },
                {
                    "x": 2.5998211669921875e+02,
                    "y": 2.2806983947753906e+02
                }
            ]
        },
        {
            "id": 240,
            "corners": [
                {
                    "x": 6.2608715820312500e+02,
                    "y": 1.2980834960937500e+02
                },
                {
                    "x": 615.0,
                    "y": 89.0
                },
                {
                    "x": 6.3858056640625000e+02,
                    "y": 2.5414619445800781e+01
                },
                {
                    "x": 6.5168414306640625e+02,
                    "y": 6.2788982391357422e+01
                }
            ]
        },
        {
            "id": 241,
            "corners": [
                {
                    "x": 3.1251397705078125e+02,
                    "y": 1.1348976898193359e+02
                },
                {
                    "x": 3.4050421142578125e+02,
                    "y": 6.7710983276367188e+01
                },
                {
                    "x": 4.0625000000000000e+02,
                    "y": 9.1750000000000000e+01
                },
                {
                    "x": 3.8277874755859375e+02,
                    "y": 1.4000440979003906e+02
                }
            ]
        },
        {
            "id": 242,
            "corners": [
                {
                    "x": 3.6965560913085938e+02,
                    "y": 3.5056210327148438e+02
                },
                {
                    "x": 3.8338146972656250e+02,
                    "y": 2.7778457641601562e+02
                },
                {
                    "x": 4.6196704101562500e+02,
                    "y": 2.8998818969726562e+02
                },
                {
                    "x": 4.5349447631835938e+02,
                    "y": 3.6103244018554688e+02
                }
            ]
        },
        {
            "id": 243,
            "corners": [
                {
                    "x": 6.4236523437500000e+02,
                    "y": 3.4590020751953125e+02
                },
                {
                    "x": 6.3385833740234375e+02,
                    "y": 2.7539282226562500e+02
                },
                {
                    "x": 6.6442510986328125e+02,
                    "y": 2.3167102050781250e+02
                },
                {
                    "x": 6.7769140625000000e+02,
                    "y": 3.0839120483398438e+02
                }
            ]
        },
        {
            "id": 244,
            "corners": [
                {
                    "x": 5.3720184326171875e+02,
                    "y": 3.1933007812500000e+02
                },
                {
                    "x": 5.8652386474609375e+02,
                    "y": 3.2997177124023438e+02
                },
                {
                    "x": 5.8278314208984375e+02,
                    "y": 3.7807809448242188e+02
                },
                {
                    "x": 5.3003637695312500e+02,
                    "y": 3.6717031860351562e+02
                }
            ]
        },
        {
            "id": 245,
            "corners": [
                {
                    "x": 5.0094607543945312e+02,
                    "y": 1.5987036132812500e+02
                },
                {
                    "x": 4.9198355102539062e+02,
                    "y": 1.0692000579833984e+02
                },
                {
                    "x": 5.5442144775390625e+02,
                    "y": 1.0928064727783203e+02
                },
                {
                    "x": 5.6650000000000000e+02,
                    "y": 1.6025000000000000e+02
                }
            ]
        },
        {
            "id": 246,
            "corners": [
                {
                    "x": 3.3561203002929688e+02,
                    "y": 2.3708741760253906e+02
                },
                {
                    "x": 3.2887506103515625e+02,
                    "y": 2.8480764770507812e+02
                },
                {
                    "x": 2.6870965576171875e+02,
                    "y": 2.7859408569335938e+02
                },
                {
                    "x": 2.7714587402343750e+02,
                    "y": 2.3105435180664062e+02
                }
            ]
        },
        {
            "id": 247,
            "corners": [
                {
                    "x": 6.2969085693359375e+02,
                    "y": 1.9045930480957031e+02
                },
                {
                    "x": 6.3692919921875000e+02,
                    "y": 1.3709455871582031e+02
                },
                {
                    "x": 6.5843951416015625e+02,
                    "y": 1.3540292358398438e+02
                },
                {
                    "x": 6.4727728271484375e+02,
                    "y": 1.9183551025390625e+02
                }
            ]
        },
        {
            "id": 248,
            "corners": [
                {
                    "x": 3.9792385864257812e+02,
                    "y": 1.7417149353027344e+02
                },
                {
                    "x": 4.4167019653320312e+02,
                    "y": 1.5800376892089844e+02
                },
                {
                    "x": 4.6698953247070312e+02,
                    "y": 1.9353982543945312e+02
                },
                {
                    "x": 4.2443218994140625e+02,
                    "y": 2.1105308532714844e+02
                }
            ]
        },
        {
            "id": 249,
            "corners": [
                {
                    "x": 2.9384918212890625e+02,
                    "y": 1.2442028045654297e+02
                },
                {
                    "x": 2.9596594238281250e+02,
                    "y": 1.6393730163574219e+02
                },
                {
                    "x": 2.3898146057128906e+02,
                    "y": 1.6421578979492188e+02
                },
                {
                    "x": 2.3803752136230469e+02,
                    "y": 1.2300068664550781e+02
                }
            ]
        }
    ]
}
